[
  {
    "item_id": "youtube:LssGRJJVDas",
    "platform_id": "LssGRJJVDas",
    "title": "US Accuses Alibaba, Baidu, BYD of Aiding Chinese Military | The China Show 6/9/2026",
    "url": "https://www.youtube.com/watch?v=LssGRJJVDas",
    "source_id": "yt_bloomberg_china",
    "source_name": "Bloomberg The China Show",
    "category": "商业 / 财经 / 投资",
    "duration_seconds": 5600,
    "published_at": "2026-06-09T07:15:04+00:00",
    "relative_path": "../../items/youtube/LssGRJJVDas/"
  },
  {
    "item_id": "youtube:yBBhd0-Os74",
    "platform_id": "yBBhd0-Os74",
    "title": "Mental Models That Change How You Think | Bill Gurley",
    "url": "https://www.youtube.com/watch?v=yBBhd0-Os74",
    "source_id": "yt_knowledge_project",
    "source_name": "The Knowledge Project Podcast",
    "category": "产品 / 创业 / 管理",
    "duration_seconds": 3680,
    "published_at": "2026-06-09T10:00:30+00:00",
    "relative_path": "../../items/youtube/yBBhd0-Os74/"
  },
  {
    "item_id": "youtube:DZt1DDmMNGk",
    "platform_id": "DZt1DDmMNGk",
    "title": "Why the AI Boom Is Just Getting Started",
    "url": "https://www.youtube.com/watch?v=DZt1DDmMNGk",
    "source_id": "yt_invest_like_best",
    "source_name": "Invest Like The Best",
    "category": "商业 / 财经 / 投资",
    "duration_seconds": 4810,
    "published_at": "2026-06-09T12:00:33+00:00",
    "relative_path": "../../items/youtube/DZt1DDmMNGk/"
  },
  {
    "item_id": "youtube:L4v-Q1Horgg",
    "platform_id": "L4v-Q1Horgg",
    "title": "Maine Votes as Graham Platner’s Past Poses New Conundrums",
    "url": "https://www.youtube.com/watch?v=L4v-Q1Horgg",
    "source_id": "yt_the_daily",
    "source_name": "The Daily",
    "category": "新闻 / 时评 / 全球议题",
    "duration_seconds": 2268,
    "published_at": "2026-06-09T14:32:32+00:00",
    "relative_path": "../../items/youtube/L4v-Q1Horgg/"
  },
  {
    "item_id": "youtube:VM1Rl7NL1Cw",
    "platform_id": "VM1Rl7NL1Cw",
    "title": "Bloomberg Surveillance 6/9/2026",
    "url": "https://www.youtube.com/watch?v=VM1Rl7NL1Cw",
    "source_id": "yt_bloomberg_surveillance",
    "source_name": "Bloomberg Surveillance Full Shows",
    "category": "商业 / 财经 / 投资",
    "duration_seconds": 8654,
    "published_at": "2026-06-09T15:08:17+00:00",
    "relative_path": "../../items/youtube/VM1Rl7NL1Cw/"
  }
]