[
  {
    "item_id": "youtube:SW-au4cjfY4",
    "platform_id": "SW-au4cjfY4",
    "title": "Joseph Torigian on Xi Zhongxun and Elite Chinese Communist Party Politics | Odd Lots",
    "url": "https://www.youtube.com/watch?v=SW-au4cjfY4",
    "source_id": "yt_odd_lots_audio",
    "source_name": "Odd Lots Audio",
    "category": "商业 / 财经 / 投资",
    "duration_seconds": 2640,
    "published_at": "2025-08-07T12:46:59+00:00",
    "relative_path": "../../items/youtube/SW-au4cjfY4/"
  },
  {
    "item_id": "youtube:Ak8KHC3XYxM",
    "platform_id": "Ak8KHC3XYxM",
    "title": "Trump Says Secondary Tariffs on China Possible | Bloomberg: The China Show 08/07/2025",
    "url": "https://www.youtube.com/watch?v=Ak8KHC3XYxM",
    "source_id": "yt_bloomberg_china",
    "source_name": "Bloomberg The China Show",
    "category": "商业 / 财经 / 投资",
    "duration_seconds": 5575,
    "published_at": "2025-08-07T13:32:30+00:00",
    "relative_path": "../../items/youtube/Ak8KHC3XYxM/"
  },
  {
    "item_id": "youtube:AmyAexM6uXg",
    "platform_id": "AmyAexM6uXg",
    "title": "Beyoncé Isn’t Giving Up on America: What We Saw on the Cowboy Carter Tour | Cannonball",
    "url": "https://www.youtube.com/watch?v=AmyAexM6uXg",
    "source_id": "yt_cannonball",
    "source_name": "Cannonball with Wesley Morris",
    "category": "文化 / 社会 / 人文",
    "duration_seconds": 2895,
    "published_at": "2025-08-07T14:00:11+00:00",
    "relative_path": "../../items/youtube/AmyAexM6uXg/"
  },
  {
    "item_id": "youtube:YAJMnZ8QkmY",
    "platform_id": "YAJMnZ8QkmY",
    "title": "Silicon Valley Wants to Optimize Your Children’s Genes | Interesting Times with Ross Douthat",
    "url": "https://www.youtube.com/watch?v=YAJMnZ8QkmY",
    "source_id": "yt_interesting_times",
    "source_name": "Interesting Times with Ross Douthat",
    "category": "新闻 / 时评 / 全球议题",
    "duration_seconds": 3984,
    "published_at": "2025-08-07T14:00:54+00:00",
    "relative_path": "../../items/youtube/YAJMnZ8QkmY/"
  },
  {
    "item_id": "youtube:m6qp7a7Mn9I",
    "platform_id": "m6qp7a7Mn9I",
    "title": "Trump Said Family Separations Would End. They’re Happening Again.",
    "url": "https://www.youtube.com/watch?v=m6qp7a7Mn9I",
    "source_id": "yt_the_daily",
    "source_name": "The Daily",
    "category": "新闻 / 时评 / 全球议题",
    "duration_seconds": 1700,
    "published_at": "2025-08-07T14:29:02+00:00",
    "relative_path": "../../items/youtube/m6qp7a7Mn9I/"
  },
  {
    "item_id": "youtube:eB9wbV5nvF8",
    "platform_id": "eB9wbV5nvF8",
    "title": "Bloomberg Surveillance 8/7/2025",
    "url": "https://www.youtube.com/watch?v=eB9wbV5nvF8",
    "source_id": "yt_bloomberg_surveillance",
    "source_name": "Bloomberg Surveillance Full Shows",
    "category": "商业 / 财经 / 投资",
    "duration_seconds": 8656,
    "published_at": "2025-08-07T15:19:41+00:00",
    "relative_path": "../../items/youtube/eB9wbV5nvF8/"
  },
  {
    "item_id": "youtube:kWcPg8t1kJ4",
    "platform_id": "kWcPg8t1kJ4",
    "title": "Artificial meat is harder than artificial intelligence — Lewis Bollard",
    "url": "https://www.youtube.com/watch?v=kWcPg8t1kJ4",
    "source_id": "yt_dwarkesh",
    "source_name": "Dwarkesh Podcast",
    "category": "科技 / AI / VC",
    "duration_seconds": 4085,
    "published_at": "2025-08-07T16:13:32+00:00",
    "relative_path": "../../items/youtube/kWcPg8t1kJ4/"
  },
  {
    "item_id": "youtube:ZttW75ys0BQ",
    "platform_id": "ZttW75ys0BQ",
    "title": "No Priors Ep. 126 | With Cloudfare CEO Matthew Prince",
    "url": "https://www.youtube.com/watch?v=ZttW75ys0BQ",
    "source_id": "yt_no_priors",
    "source_name": "No Priors Podcast",
    "category": "科技 / AI / VC",
    "duration_seconds": 2717,
    "published_at": "2025-08-07T19:23:58+00:00",
    "relative_path": "../../items/youtube/ZttW75ys0BQ/"
  }
]