{
  "schema_version": 1,
  "item_id": "youtube:-Qm1_On71Oo",
  "metadata": {
    "item_id": "youtube:-Qm1_On71Oo",
    "platform": "youtube",
    "platform_id": "-Qm1_On71Oo",
    "source_id": "yt_lex_fridman",
    "source_name": "Lex Fridman",
    "category": "文化 / 科学 / 教育",
    "title": "Dave Hone: T-Rex, Dinosaurs, Extinction, Evolution, and Jurassic Park | Lex Fridman Podcast #480",
    "url": "https://www.youtube.com/watch?v=-Qm1_On71Oo",
    "published_at": "2025-09-04T19:56:59+00:00",
    "report_date": "2025-09-05",
    "duration_seconds": 12986,
    "language": "en"
  },
  "generation": {
    "script": "trae_agent",
    "model": "trae_agent",
    "quality": "trae_agent_validated"
  },
  "digest": {
    "short_title": "霸王龙深度解剖",
    "one_liner": "古生物学家详解霸王龙的解剖学、行为与演化奥秘",
    "why_it_matters": "揭示恐龙如何生活、捕猎和灭绝，帮助理解生命演化的底层逻辑",
    "summary": "古生物学家Dave Hone做客Lex Fridman播客，围绕霸王龙展开了一场深入而生动的科普对话。Hone从霸王龙的体型切入——体长约12米，体重约7吨，相当于一头陆地上的虎鲸——详细讲解了其巨大的头骨、网球大小的眼球、厚实有力的牙齿以及极小的前肢。他指出霸王龙的咬合力极其惊人，牙齿不仅长而且粗壮，能够轻松击穿骨骼。前肢虽然很小，但韧带窝显示手指其实相当有力，只是功能有限。\n\n关于运动方式，Hone解释了霸王龙的双足行走机制依赖于巨大的尾部肌肉群驱动大腿向后蹬，而非像哺乳动物那样依赖臀部和腿部的肌肉分布。最新研究估计其最高时速约40公里，属于力量型快走而非奔跑。足部有一种独特的中间跖骨锁定结构，提高了行走的能量效率。\n\n在捕猎行为方面，Hone提出了一个核心观点：霸王龙主要捕食幼年食草恐龙而非成年三角龙。这符合现代掠食者的普遍规律——捕食对象通常仅为自身体重的5%-20%。胃容物和咬痕化石证据均支持这一结论。他对《侏罗纪公园》中静止不动就看不见霸王龙的说法进行了辟谣，指出霸王龙拥有恐龙时代最大的眼球，视力极其出色，可能主要在夜间活动。\n\n关于群体狩猎，Hone持保守态度。他认为虽然很多恐龙确实群居，但目前没有足够证据证明霸王龙或迅猛龙会协同狩猎。他以狮子群猎而老虎独居为例说明，即使近缘物种的社交行为也可能截然不同。化石记录中多条足迹并行或多种个体聚集并不能直接等同于协同捕猎。\n\n节目还探讨了恐龙的性别鉴定（髓质骨是判断产卵期雌性的关键证据）、头冠和角的社交-性选择功能、羽毛的演化（保温和展示双重功能）、鸟类作为恐龙直系后裔的演化关系，以及6600万年前白垩纪大灭绝中鸟类为何幸存（体型小是关键因素）。Hone还强调了演化中的妥协本质——进化不是完美化，而是在已有蓝图上做修改。",
    "core_points": [
      "霸王龙体重约7吨，是地球历史上最强大的陆地掠食者之一，体型远超同生态系统中的其他食肉恐龙",
      "霸王龙主要捕食幼年恐龙而非成年大型猎物，这符合现代掠食者的普遍生态规律",
      "霸王龙的视力极其出色，眼球为网球大小，可能是夜行性动物",
      "目前没有足够证据证明恐龙存在协同狩猎行为，尽管群居可能性很高",
      "鸟类是恐龙的直系后裔，羽毛在霸王龙等兽脚类恐龙中早已存在，最初功能可能是保温和性展示",
      "演化的本质是妥协和修改，而非追求完美——descent with modification"
    ],
    "key_facts": [
      "霸王龙体长约12米，体重约7吨，头骨大到可以容纳一个成年人",
      "霸王龙最高时速估计约40公里/时（25英里/时），属于力量型快走",
      "霸王龙眼球为网球大小，是恐龙时代最大的眼球之一",
      "掠食者通常捕食自身体重5%-20%的猎物",
      "海洋翻车鱼（Mola mola）单次可释放多达3亿颗卵",
      "鸟类在白垩纪之前就已与恐龙共存了约1亿年",
      "最早的带羽毛霸王龙化石可追溯到1.65亿年前的中侏罗世"
    ],
    "takeaways": [
      "恐龙研究正在从发现新物种转向理解行为与生态，化石中的咬痕、足迹和骨组织结构是关键线索",
      "《侏罗纪公园》中的许多常识其实是错误的——迅猛龙体型被放大、霸王龙视力极差不靠移动感知猎物等",
      "演化是一个极其漫长的大数游戏：百万级种群 × 百万年 × 千级后代 = 天文数字的变异机会",
      "理解现代动物的行为和生态可以为推断恐龙行为提供有价值的类比框架"
    ],
    "guests": [
      "Dave Hone - 古生物学家，恐龙行为与生态学专家，Terrible Lizards播客联合主持人"
    ],
    "topics": [
      "古生物学",
      "霸王龙",
      "恐龙演化",
      "侏罗纪公园",
      "白垩纪灭绝",
      "鸟类起源",
      "性选择",
      "捕食生态学",
      "群体行为"
    ],
    "tensions": [
      "群体狩猎争议：化石证据（多条足迹并行、多个体聚集）是否等于协同捕猎？Hone认为证据不足",
      "功能推断的局限性：单一特征（如三角龙的角、霸王龙的前肢）可能有多种功能，不应简化为二元解释",
      "演化驱动力之争：长颈鹿的脖子究竟是取食竞争还是性选择的产物？"
    ],
    "quote": "Evolution is rolling dice, but it gets to keep the sixes. | 演化是在掷骰子，但它可以保留所有的六点。",
    "importance_score": 3,
    "content_density": "high",
    "quality": "trae_agent_validated"
  }
}