[
  {
    "item_id": "youtube:XTnPH-XENKw",
    "platform_id": "XTnPH-XENKw",
    "title": "Xi Extends Courtship of Global South with BRICS Address | The China Show 9/8/2025",
    "url": "https://www.youtube.com/watch?v=XTnPH-XENKw",
    "source_id": "yt_bloomberg_china",
    "source_name": "Bloomberg The China Show",
    "category": "商业 / 财经 / 投资",
    "duration_seconds": 5568,
    "published_at": "2025-09-08T05:18:05+00:00",
    "relative_path": "../../items/youtube/XTnPH-XENKw/"
  },
  {
    "item_id": "youtube:9KXOO3gK5wo",
    "platform_id": "9KXOO3gK5wo",
    "title": "America’s Big Agriculture Problem Is Getting Worse",
    "url": "https://www.youtube.com/watch?v=9KXOO3gK5wo",
    "source_id": "yt_bloomberg_originals",
    "source_name": "Bloomberg Originals",
    "category": "商业 / 财经 / 投资",
    "duration_seconds": 1123,
    "published_at": "2025-09-08T08:00:11+00:00",
    "relative_path": "../../items/youtube/9KXOO3gK5wo/"
  },
  {
    "item_id": "youtube:Sd7cCpoJjbI",
    "platform_id": "Sd7cCpoJjbI",
    "title": "Josh Wolfe on AI and the Breaking of Silicon Valley's Social Contract | Odd Lots",
    "url": "https://www.youtube.com/watch?v=Sd7cCpoJjbI",
    "source_id": "yt_odd_lots",
    "source_name": "Odd Lots",
    "category": "商业 / 财经 / 投资",
    "duration_seconds": 3025,
    "published_at": "2025-09-08T08:00:28+00:00",
    "relative_path": "../../items/youtube/Sd7cCpoJjbI/"
  },
  {
    "item_id": "youtube:cW65phBjzi0",
    "platform_id": "cW65phBjzi0",
    "title": "When the National Guard Comes to Town",
    "url": "https://www.youtube.com/watch?v=cW65phBjzi0",
    "source_id": "yt_the_daily",
    "source_name": "The Daily",
    "category": "新闻 / 时评 / 全球议题",
    "duration_seconds": 2208,
    "published_at": "2025-09-08T14:23:20+00:00",
    "relative_path": "../../items/youtube/cW65phBjzi0/"
  },
  {
    "item_id": "youtube:xNpQc7Um1ds",
    "platform_id": "xNpQc7Um1ds",
    "title": "Bloomberg Surveillance 9/8/2025",
    "url": "https://www.youtube.com/watch?v=xNpQc7Um1ds",
    "source_id": "yt_bloomberg_surveillance",
    "source_name": "Bloomberg Surveillance Full Shows",
    "category": "商业 / 财经 / 投资",
    "duration_seconds": 8654,
    "published_at": "2025-09-08T15:13:57+00:00",
    "relative_path": "../../items/youtube/xNpQc7Um1ds/"
  },
  {
    "item_id": "youtube:vvj_J2tB2Ag",
    "platform_id": "vvj_J2tB2Ag",
    "title": "Steve Bannon: Silicon Valley Is Turning Us Into ‘Digital Serfs’",
    "url": "https://www.youtube.com/watch?v=vvj_J2tB2Ag",
    "source_id": "yt_interesting_times",
    "source_name": "Interesting Times with Ross Douthat",
    "category": "新闻 / 时评 / 全球议题",
    "duration_seconds": 1084,
    "published_at": "2025-09-08T17:01:19+00:00",
    "relative_path": "../../items/youtube/vvj_J2tB2Ag/"
  }
]