{
  "schema_version": 1,
  "item_id": "youtube:NRLNO_KOh9I",
  "platform": "youtube",
  "platform_id": "NRLNO_KOh9I",
  "transcript_sha256": "cc22aa5fb7be1ec58392679438aaa08023ec9b621c5a1f2a90d48067a1141a28",
  "metadata": {
    "item_id": "youtube:NRLNO_KOh9I",
    "platform": "youtube",
    "platform_id": "NRLNO_KOh9I",
    "source_id": "yt_odd_lots_audio",
    "source_name": "Odd Lots Audio",
    "category": "商业 / 财经 / 投资",
    "title": "How the Speed of a Trade Got Down to Nearly the Speed of Light | Odd Lots",
    "url": "https://www.youtube.com/watch?v=NRLNO_KOh9I",
    "published_at": "2026-03-02T17:00:37+00:00",
    "report_date": "2026-03-03",
    "duration_seconds": 3338,
    "language": "en"
  },
  "generation": {
    "script": "trae_agent",
    "model": "trae_agent",
    "quality": "trae_agent_validated"
  },
  "digest": {
    "short_title": "交易速度逼近光速",
    "one_liner": "高频交易如何从毫秒竞争到纳秒级别的速度军备竞赛",
    "why_it_matters": "揭示交易速度竞赛背后的市场结构、物理限制及其对资本配置效率的深层影响",
    "summary": [
      "Island交易所在1990年代末以2毫秒撮合速度开创电子交易先河，比前代系统快千倍，与自动化交易系统形成天然契合，引发传统交易所被迫技术升级的连锁反应。",
      "2005年NASDAQ收购Island、纽交所收购Archipelago，标志电子化交易成为主流。此后交易速度从毫秒演进到微秒再到纳秒，光速成为不可逾越的物理极限。",
      "交易基础设施演变为速度战场：从光纤到Spread Networks专线再到微波链路，数据中心共址与等长电缆规则重塑市场公平竞争格局。",
      "做市商填充订单簿提供流动性，流动性获取者消耗订单簿获利。当期货价格变动时，做市商急于取消陈旧订单，获取者争相执行，形成纳秒级军备竞赛。",
      "高频交易公司通常规模小、结构扁平、用自有资本运营，创始人深度参与风控。与银行冗长的IT审批流程形成鲜明对比。",
      "技术效率提升未降低金融中介成本：1880年代到2015年单位成本基本不变，效率增益被金融业高薪酬所吞噬。AI与高频交易面临类似收益递减困境。"
    ],
    "core_points": [
      "Island交易所2毫秒撮合速度开启高频交易时代，电子订单簿加自动撮合取代人工谈判",
      "延迟从毫秒到微秒再到纳秒，十分之一秒是人类感知时间下限，机器早已超越人类反应能力",
      "速度竞争从服务器共址发展到光纤专线再到微波传输，光纤中光速仅为真空光速的三分之二",
      "做市商提供流动性与流动性获取者之间的军备竞赛构成高频交易核心张力",
      "高频交易公司小规模扁平结构加自有资本运营优于银行官僚体制的采购审批流程",
      "金融中介单位成本从1880年代到2015年未下降，效率增益被金融业高薪酬吸收",
      "AI投入与智能呈对数收益递减关系，与高频交易速度军备竞赛面临相似困境"
    ],
    "key_facts": [
      {
        "label": "Island撮合速度",
        "value": "2毫秒",
        "context": "1990年代末Island撮合引擎速度，比前代Instinet系统快约千倍",
        "source_refs": []
      },
      {
        "label": "交易所电子化",
        "value": "2005年",
        "context": "NASDAQ收购Island、纽交所收购Archipelago完成电子化转型",
        "source_refs": []
      },
      {
        "label": "延迟演进",
        "value": "毫秒到微秒到纳秒",
        "context": "2011年毫秒级，两三年后微秒级，2018至2020年纳秒级",
        "source_refs": []
      },
      {
        "label": "光纤光速比例",
        "value": "三分之二",
        "context": "光在光纤玻璃中的传播速度仅为真空光速的三分之二",
        "source_refs": []
      },
      {
        "label": "金融中介成本",
        "value": "1880年代到2015年未下降",
        "context": "Thomas Philippon研究显示单位金融中介成本百年未降",
        "source_refs": []
      },
      {
        "label": "AI对数关系",
        "value": "年2月",
        "context": "Sam Altman称系统智能与投入资源呈对数关系即收益递减",
        "source_refs": []
      }
    ],
    "takeaways": [
      "速度军备竞赛不会终结但受经济回报约束，可回收利润限制技术投入上限",
      "金融技术进步未必降低中介成本，效率增益可能被行业高薪所吞噬"
    ],
    "guests": [
      "Donald MacKenzie，爱丁堡大学社会学教授，著有Trading at the Speed of Light"
    ],
    "topics": [
      "高频交易",
      "交易速度",
      "市场结构"
    ],
    "tensions": [
      "做市商提供流动性与流动性获取者之间的对立角色及相互指责",
      "速度军备竞赛带来社会资源消耗但可回收利润有限形成经济约束",
      "银行因官僚体制与自营交易禁令难以与小型灵活的高频交易公司竞争"
    ],
    "quote": {
      "text": "你永远无法到达零，但可以无限接近",
      "speaker": "Donald MacKenzie",
      "kind": "paraphrase"
    },
    "importance_score": 4,
    "content_density": "high",
    "quality": "trae_agent_validated"
  }
}
