{
  "schema_version": 2,
  "date": "2026-05-26",
  "title": "2026-05-26 YouTube 更新日报（草稿）",
  "reader_mode": "breakfast",
  "item_count": 4,
  "read_minutes": 3,
  "platform_counts": {
    "YouTube": 4
  },
  "category_counts": {
    "商业 / 财经 / 投资": 3,
    "文化 / 社会 / 人文": 1
  },
  "themes": [
    "商业",
    "文化"
  ],
  "top_items": [
    3,
    2,
    1
  ],
  "items": [
    {
      "url": "https://www.youtube.com/watch?v=yYkBpzq5Sqw",
      "original_title": "Rolls-Royce CEO Tufan Erginbilgiç Shares His Turnaround Playbook",
      "source_name": "Leaders with Francine Lacqua",
      "platform": "YouTube",
      "published_at": "2026-05-25T05:00:18+00:00",
      "duration": 1425,
      "category": "商业 / 财经 / 投资",
      "short_title": "Rolls-Royce CEO Tufa…",
      "one_liner": "Kind: captions Language: en I am dem…",
      "why_it_matters": "If you are working with me, there's this trust element.",
      "summary": [
        "If you are working with me, there's this trust element.",
        "I'm going to be very fair, very transparent."
      ],
      "core_points": [
        "Kind: captions Language: en I am demanding.",
        "If you are working with me, there's this trust element.",
        "I'm going to be very fair, very transparent."
      ],
      "key_facts": [],
      "takeaways": [
        "先用 30 秒结论判断是否值得打开原节目。",
        "涉及数据或决策时回到原字幕核对上下文。"
      ],
      "guests": [],
      "topics": [
        "商业"
      ],
      "tensions": [],
      "quote": null,
      "importance_score": 3,
      "content_density": "standard",
      "quality": "deterministicfallback"
    },
    {
      "url": "https://www.youtube.com/watch?v=CVYY2xbU3lU",
      "original_title": "China Investigates Deadly Coal Mine Blast | The China Show 5/25/2026",
      "source_name": "Bloomberg The China Show",
      "platform": "YouTube",
      "published_at": "2026-05-25T05:26:31+00:00",
      "duration": 5575,
      "category": "商业 / 财经 / 投资",
      "short_title": "China Investigates D…",
      "one_liner": "Kind: captions Language: en It's 9:…",
      "why_it_matters": "You're watching the China Show.",
      "summary": [
        "You're watching the China Show.",
        "I'm Ivon Man and I'm Averil Hong in Singapore."
      ],
      "core_points": [
        "Kind: captions Language: en It's 9:00 a.m. in Shanghai and Shenzhen.",
        "You're watching the China Show.",
        "I'm Ivon Man and I'm Averil Hong in Singapore."
      ],
      "key_facts": [],
      "takeaways": [
        "先用 30 秒结论判断是否值得打开原节目。",
        "涉及数据或决策时回到原字幕核对上下文。"
      ],
      "guests": [],
      "topics": [
        "商业"
      ],
      "tensions": [],
      "quote": null,
      "importance_score": 3,
      "content_density": "standard",
      "quality": "deterministicfallback"
    },
    {
      "url": "https://www.youtube.com/watch?v=vc8VDEt2us4",
      "original_title": "What It Takes to Run One of London's Most Popular Pubs | Odd Lots",
      "source_name": "Odd Lots",
      "platform": "YouTube",
      "published_at": "2026-05-25T08:18:43+00:00",
      "duration": 4214,
      "category": "商业 / 财经 / 投资",
      "short_title": "What It Takes to Run On…",
      "one_liner": "Kind: captions Language: en Hello a…",
      "why_it_matters": "I'm Joe Weisenthal &gt;&gt; and I'm Tracy Aloway. &gt;&gt; Today you'r…",
      "summary": [
        "I'm Joe Weisenthal &gt;&gt; and I'm Tracy Aloway. &gt;&gt; Today you're going to be treated to a special two-part episode.",
        "We are here in London and so we wanted to learn about the business of pubs of course and so we are bringing you first an interview with famed publican Rogers."
      ],
      "core_points": [
        "Kind: captions Language: en Hello and welcome to another episode of the OddLots podcast.",
        "I'm Joe Weisenthal &gt;&gt; and I'm Tracy Aloway. &gt;&gt; Today you're going to be treated to a special two…",
        "We are here in London and so we wanted to learn about the business of pubs of course and so we are bringing you fi…"
      ],
      "key_facts": [],
      "takeaways": [
        "先用 30 秒结论判断是否值得打开原节目。",
        "涉及数据或决策时回到原字幕核对上下文。"
      ],
      "guests": [],
      "topics": [
        "商业"
      ],
      "tensions": [],
      "quote": null,
      "importance_score": 3,
      "content_density": "standard",
      "quality": "deterministicfallback"
    },
    {
      "url": "https://www.youtube.com/watch?v=UWBhxCcaoVU",
      "original_title": "The Trust Diagnosis | Malcolm Gladwell's Revisionist History",
      "source_name": "Revisionist History",
      "platform": "YouTube",
      "published_at": "2026-05-25T13:00:29+00:00",
      "duration": 2350,
      "category": "文化 / 社会 / 人文",
      "short_title": "The Trust Diagnosis |…",
      "one_liner": "Kind: captions Language: en [music…",
      "why_it_matters": "I've known him for years.",
      "summary": [
        "I've known him for years.",
        "He's in his 70s, lives outside Washington, D.C."
      ],
      "core_points": [
        "Kind: captions Language: en [music] &gt;&gt; Pushkin I have a friend named Dan.",
        "I've known him for years.",
        "He's in his 70s, lives outside Washington, D.C."
      ],
      "key_facts": [],
      "takeaways": [
        "先用 30 秒结论判断是否值得打开原节目。",
        "涉及数据或决策时回到原字幕核对上下文。"
      ],
      "guests": [],
      "topics": [
        "文化"
      ],
      "tensions": [],
      "quote": null,
      "importance_score": 3,
      "content_density": "standard",
      "quality": "deterministicfallback"
    }
  ],
  "platform_scope": "youtube",
  "mode": "youtube_only_draft"
}